codextextpipe/__init__.py
codextextpipe/config/__init__.py
codextextpipe/config/config.py
codextextpipe/config/nltk.py
codextextpipe/core/__init__.py
codextextpipe/core/classifier.py
codextextpipe/core/recommender.py
codextextpipe/data/__init__.py
codextextpipe/data/cleaner.py
codextextpipe/data/loader.py
codextextpipe/data/model_io.py
codextextpipe/data/tokenizer.py
codextextpipe/data/vectorizer.py
codextextpipe/pipeline/__init__.py
codextextpipe/pipeline/category_generator.py
codextextpipe/pipeline/sentiment_pipeline.py
codextextpipe/pipeline/suggestion_pipeline.py
codextextpipe/utils/__init__.py
codextextpipe/utils/logger.py
codextextpipe/utils/metrics.py
codextextpipe-0.1.3.dist-info/licenses/LICENSE
codextextpipe-0.1.3.dist-info/METADATA
codextextpipe-0.1.3.dist-info/WHEEL
codextextpipe-0.1.3.dist-info/top_level.txt
codextextpipe-0.1.3.dist-info/RECORD
