Metadata-Version: 2.4
Name: codextextpipe
Version: 0.1.3
Summary: All-in-one tool for text processing
Author-email: Textpipe Team <codexesto@gmail.com>
Keywords: text processing,text analysis,natural language processing
Classifier: Programming Language :: Python :: 3
Classifier: Operating System :: OS Independent
Classifier: Development Status :: 4 - Beta
Classifier: Intended Audience :: Developers
Classifier: Natural Language :: English
Requires-Python: >=3.7
License-File: LICENSE
Requires-Dist: scikit-learn
Requires-Dist: nltk
Requires-Dist: sphinx
Requires-Dist: pytest
Requires-Dist: pandas
Requires-Dist: bs4
Dynamic: license-file
